MANIFEST.in
README.rst
setup.cfg
setup.py
src/django_smscoin.egg-info/PKG-INFO
src/django_smscoin.egg-info/SOURCES.txt
src/django_smscoin.egg-info/dependency_links.txt
src/django_smscoin.egg-info/not-zip-safe
src/django_smscoin.egg-info/requires.txt
src/django_smscoin.egg-info/top_level.txt
src/smscoin/__init__.py
src/smscoin/admin.py
src/smscoin/fields.py
src/smscoin/models.py
src/smscoin/settings.py
src/smscoin/tests.py
src/smscoin/utils.py
src/smscoin/locale/ru/LC_MESSAGES/django.mo
src/smscoin/locale/ru/LC_MESSAGES/django.po
src/smscoin/management/__init__.py
src/smscoin/management/commands/__init__.py
src/smscoin/management/commands/update_sms_tariff.py
src/smscoin/migrations/0001_initial.py
src/smscoin/migrations/0002_auto__chg_field_provider_notice.py
src/smscoin/migrations/0003_auto__add_field_provider_modified.py
src/smscoin/migrations/__init__.py
src/smscoin/templates/smscoin_help.html
src/smscoin/templatetags/__init__.py
src/smscoin/templatetags/smscoin_tags.py