Metadata-Version: 1.1
Name: django-smscoin
Version: 0.1
Summary: Django application to use sms processing system http://smscoin.com/
Home-page: https://github.com/Arpaso/smscoin
Author: Arpaso
Author-email: arvid@arpaso.com
License: UNKNOWN
Download-URL: https://github.com/Arpaso/smscoin/tarball/0.1
Platform: UNKNOWN
Classifier: Programming Language :: Python
Classifier: Programming Language :: Python :: 2
Classifier: Development Status :: 3 - Alpha
Classifier: Environment :: Web Environment
Classifier: Intended Audience :: Developers
Classifier: License :: OSI Approved :: GNU Library or Lesser General Public License (LGPL)
Classifier: Operating System :: OS Independent
Classifier: Topic :: Software Development :: Libraries :: Python Modules
Classifier: Framework :: Django
